{
  "yokohama": [
    {
      "name": "요코하마 베이 호텔 도큐",
      "nameJa": "横浜ベイホテル東急",
      "map": "横浜ベイホテル東急",
      "area": "미나토미라이",
      "near": "미나토미라이역 도보 약 1분, 파시피코 요코하마 바로 옆",
      "price": "1박 약 3만~5만 엔대",
      "note": "회장과 가장 가까운 호텔 중 하나. 역과 직결되어 비 안 맞고 이동 가능, 야경 전망이 좋아 가족 여행에 인기."
    },
    {
      "name": "요코하마 그랜드 인터컨티넨탈 호텔",
      "nameJa": "横浜グランドインターコンチネンタルホテル",
      "map": "横浜グランドインターコンチネンタルホテル",
      "area": "미나토미라이",
      "near": "파시피코 요코하마 도보 약 5분, 미나토미라이역 도보 약 7분",
      "price": "1박 약 3만~5만 엔대",
      "note": "회장 바로 옆 항구 전망 호텔. 관람차·베이브리지 야경 객실이 가족에게 호평."
    },
    {
      "name": "요코하마 로열파크 호텔 (랜드마크타워)",
      "nameJa": "横浜ロイヤルパークホテル",
      "map": "横浜ロイヤルパークホテル",
      "area": "미나토미라이",
      "near": "미나토미라이역 도보 약 3분, 파시피코 요코하마 도보 약 8분",
      "price": "1박 약 3만~6만 엔대",
      "note": "랜드마크타워 고층에 위치. 전망대급 뷰가 강점이라 아이들이 좋아함."
    },
    {
      "name": "아파호텔&리조트 요코하마 베이타워",
      "nameJa": "アパホテル＆リゾート 横浜ベイタワー",
      "map": "アパホテル＆リゾート 横浜ベイタワー",
      "area": "바샤미치/사쿠라기초 인근",
      "near": "바샤미치역 도보 약 3분, 사쿠라기초역 도보 약 9분(회장까지 한 정거장)",
      "price": "1박 약 1.5만~3만 엔대",
      "note": "24시간 대욕장·옥상 풀(기간 한정)·키즈 매트 대여 등 가족 편의시설 충실. 가성비 양호."
    },
    {
      "name": "사쿠라기초 인근 비즈니스호텔",
      "nameJa": "桜木町駅周辺 ビジネスホテル",
      "map": "桜木町駅",
      "area": "사쿠라기초",
      "near": "사쿠라기초역 도보 약 5분(회장까지 한 정거장)",
      "price": "1박 약 8천~1.5만 엔대",
      "note": "대욕장·조식 뷔페를 갖춘 합리적 가격의 비즈니스호텔이 모인 지역. 예산 절약형 가족에게 적합."
    }
  ],
  "chiba": [
    {
      "name": "호텔 뉴오타니 마쿠하리",
      "nameJa": "ホテルニューオータニ幕張",
      "map": "ホテルニューオータニ幕張",
      "area": "카이힌마쿠하리",
      "near": "마쿠하리 멧세 바로 옆(도보 약 2~3분, 2층 연결통로 직결)",
      "price": "1박 약 2만~4만 엔(2인)",
      "note": "회장 바로 옆 대형 고급 호텔. 연락통로로 직결되어 날씨 영향 없이 이동. 레스토랑 다수로 가족 여행에 편안."
    },
    {
      "name": "호텔 프랑크스",
      "nameJa": "ホテルフランクス",
      "map": "ホテルフランクス",
      "area": "카이힌마쿠하리",
      "near": "카이힌마쿠하리역 도보 약 3분 / 마쿠하리 멧세 도보 약 5~6분",
      "price": "1박 약 1.2만~2.5만 엔(2인)",
      "note": "역·회장과 가장 가까운 축. 위치가 최고라 대회 참가자에게 인기, 빨리 매진됨."
    },
    {
      "name": "아파호텔 & 리조트 도쿄베이 마쿠하리",
      "nameJa": "アパホテル&リゾート 東京ベイ幕張",
      "map": "アパホテル&リゾート 東京ベイ幕張",
      "area": "카이힌마쿠하리(베이존)",
      "near": "카이힌마쿠하리역 도보 약 7분",
      "price": "1박 약 9천~2만 엔(2인)",
      "note": "대형 리조트형. 대욕장·수영장 보유로 자녀 동반 가족에 인기. 객실 수가 많아 자리 잡기 수월."
    },
    {
      "name": "호텔 그린타워 마쿠하리",
      "nameJa": "ホテルグリーンタワー幕張",
      "map": "ホテルグリーンタワー幕張",
      "area": "카이힌마쿠하리",
      "near": "카이힌마쿠하리역 남쪽 출구 도보 약 3분 / 마쿠하리 멧세 도보 약 3~5분",
      "price": "1박 약 8천~1.8만 엔(2인)",
      "note": "가성비 좋은 편. 레스토랑·조식 뷔페 보유, 화실(다다미방)도 있어 가족에게 적합."
    },
    {
      "name": "호텔 스프링스 마쿠하리",
      "nameJa": "ホテルスプリングス幕張",
      "map": "ホテルスプリングス幕張",
      "area": "카이힌마쿠하리",
      "near": "카이힌마쿠하리역 도보 약 8분 / 마쿠하리 멧세 도보 약 10분",
      "price": "1박 약 1만~2만 엔(2인)",
      "note": "레스토랑·연회장 갖춘 시티호텔. 합리적 가격에 가족 객실 옵션 있음."
    }
  ],
  "miyagi": [
    {
      "name": "호텔 메트로폴리탄 센다이",
      "nameJa": "ホテルメトロポリタン仙台",
      "map": "ホテルメトロポリタン仙台",
      "area": "센다이역 서쪽 출구",
      "near": "JR 센다이역 서쪽 출구 도보 약 1분",
      "price": "1박 약 1.8만~3만 엔대(2인)",
      "note": "JR동일본 직영 시티호텔. 역과 사실상 직결이라 짐 많은 가족·겨울 이동에 최적. 회장행 버스 타는 서쪽 출구 바로 앞."
    },
    {
      "name": "다이와 로이넷 호텔 센다이",
      "nameJa": "ダイワロイネットホテル仙台",
      "map": "ダイワロイネットホテル仙台",
      "area": "센다이역 동쪽 출구",
      "near": "JR 센다이역 동쪽 출구 도보 약 2분",
      "price": "1박 약 1.2만~2만 엔대(2인)",
      "note": "객실이 넓은 편이라 자녀 동반 가족에 적합. 가격 대비 무난한 중급 호텔."
    },
    {
      "name": "미쓰이 가든 호텔 센다이",
      "nameJa": "三井ガーデンホテル仙台",
      "map": "三井ガーデンホテル仙台",
      "area": "히로세도리 인근",
      "near": "지하철 히로세도리역 도보 약 1분, 센다이역 도보 약 8~10분",
      "price": "1박 약 1.4만~2.4만 엔대(2인)",
      "note": "최상층에 대욕장(온천식)이 있어 추운 겨울 자녀와 함께 좋음. 6세 이하 첨잠 무료, 아동 어메니티 제공."
    },
    {
      "name": "센다이 워싱턴 호텔",
      "nameJa": "仙台ワシントンホテル",
      "map": "仙台ワシントンホテル",
      "area": "센다이역 서쪽 출구",
      "near": "JR 센다이역 서쪽 출구 도보 약 3분",
      "price": "1박 약 1.1만~1.8만 엔대(2인)",
      "note": "베드가드·아동용 타월·잠옷 무료 대여 등 가족 친화 서비스. 가성비 양호."
    },
    {
      "name": "도요코인 센다이역 서쪽출구 중앙",
      "nameJa": "東横INN仙台駅西口中央",
      "map": "東横INN仙台駅西口中央",
      "area": "센다이역 서쪽 출구",
      "near": "JR 센다이역 서쪽 출구 도보 약 5분",
      "price": "1박 약 8천~1.3만 엔대(2인)",
      "note": "전국 체인 저가 호텔로 예약 쉽고 무료 조식 제공. 알뜰 가족 여행에 적합."
    }
  ],
  "osaka": [
    {
      "name": "아트호텔 오사카 베이타워",
      "nameJa": "アートホテル大阪ベイタワー",
      "map": "アートホテル大阪ベイタワー",
      "area": "벤텐초",
      "near": "추오선 벤텐초역 직결, 회장(코스모스퀘어)까지 추오선 약 7분",
      "price": "1박 약 1.5만~3만 엔(2인)",
      "note": "벤텐초역 직결로 회장 접근 최고. 51층 스카이뷔페 인기, 초등생 이하 첨잠 무료. JR 순환선 직결로 시내 이동도 편리."
    },
    {
      "name": "호텔 후쿠라시아 오사카 베이",
      "nameJa": "ホテルフクラシア大阪ベイ",
      "map": "ホテルフクラシア大阪ベイ",
      "area": "코스모스퀘어(난코)",
      "near": "코스모스퀘어역에서 무료 서클버스 약 5분, 인텍스 오사카 인접",
      "price": "1박 약 1만~1.8만 엔(2인)",
      "note": "회장과 가장 가까운 호텔 중 하나. 대욕장 완비, 주말·공휴일 무료 송영버스 운행. 가성비 좋고 조용함."
    },
    {
      "name": "오사카 아카데미아",
      "nameJa": "大阪アカデミア",
      "map": "大阪アカデミア",
      "area": "코스모스퀘어(난코)",
      "near": "코스모스퀘어역에서 무료 셔틀버스, 인텍스 오사카 바로 옆",
      "price": "1박 약 9천~1.5만 엔(2인)",
      "note": "인텍스 오사카 바로 옆. 무료 셔틀·대욕장·사우나·노천탕 이용 가능. 대회 당일 아주 편리."
    },
    {
      "name": "베셀인 난바",
      "nameJa": "ベッセルイン難波",
      "map": "ベッセルイン難波",
      "area": "난바",
      "near": "오사카메트로 난바역 도보 약 2분(회장까지 미도스지선→혼마치 환승→추오선)",
      "price": "1박 약 1만~1.6만 엔(2인)",
      "note": "18세 이하 첨잠 무료로 가족 가성비 우수. 무료 조식, 도톤보리·구로몬시장 도보권."
    },
    {
      "name": "호텔 시걸 텐포잔 오사카",
      "nameJa": "ホテルシーガルてんぽーざん大阪",
      "map": "ホテルシーガルてんぽーざん大阪",
      "area": "텐포잔·오사카항",
      "near": "추오선 오사카항역 도보 약 5분(회장까지 추오선 2정거장)",
      "price": "1박 약 1.2만~2.2만 엔(2인)",
      "note": "전 객실 오션뷰·넓은 객실. 카이유칸(수족관) 도보 3분으로 자녀 동반 관광에 최적."
    }
  ],
  "aichi": [
    {
      "name": "중부국제공항 센트레아호텔",
      "nameJa": "中部国際空港 セントレアホテル",
      "map": "中部国際空港 セントレアホテル",
      "area": "센트레아(공항섬)",
      "near": "센트레아역 정면, 회장까지 도보권",
      "price": "1박 약 1.5만~3만 엔(2인)",
      "note": "공항·역 직결 배리어프리. 회장 도보 이동 가능해 대회 당일 최강 입지. 가족실 있음."
    },
    {
      "name": "컴포트호텔 중부국제공항",
      "nameJa": "コンフォートホテル中部国際空港",
      "map": "コンフォートホテル中部国際空港",
      "area": "센트레아(공항섬)",
      "near": "공항·역에서 지붕 있는 공중통로로 도보 약 5분, 회장 도보권",
      "price": "1박 약 1만~1.8만 엔(2인, 조식 무료)",
      "note": "무료 조식·전 객실 금연. 비 와도 젖지 않는 연결 통로로 어린이 동반 가성비 좋음."
    },
    {
      "name": "토요코인 중부국제공항 1",
      "nameJa": "東横INN中部国際空港1",
      "map": "東横INN中部国際空港1",
      "area": "센트레아(공항섬 부근)",
      "near": "공항역에서 도보 약 5~7분, 무료 셔틀버스 운행",
      "price": "1박 약 9천~1.5만 엔(2인, 조식 무료)",
      "note": "무료 조식·24시간 편의점 병설. 한국인에게 익숙한 체인, 합리적 가격."
    },
    {
      "name": "베셀호텔 캄파나 나고야",
      "nameJa": "ベッセルホテルカンパーナ名古屋",
      "map": "ベッセルホテルカンパーナ名古屋",
      "area": "나고야역",
      "near": "나고야역에서 도보 약 9분",
      "price": "1박 약 1.2만~2.2만 엔(2인, 조식 무료)",
      "note": "사우나 딸린 대욕장, 조식에 히츠마부시·미소카츠 등 나고야 명물. 18세 이하 첨잠 무료·기저귀 무료로 자녀 동반에 최적."
    },
    {
      "name": "나고야 메리어트 어소시아호텔",
      "nameJa": "名古屋マリオットアソシアホテル",
      "map": "名古屋マリオットアソシアホテル",
      "area": "나고야역",
      "near": "JR 나고야역 바로 위 직결(고층)",
      "price": "1박 약 3만~5.5만 엔(2인)",
      "note": "역 직결이라 자녀 동반 이동 최소화. 뷔페·키즈 메뉴 충실, 고층 전망. 고급형."
    }
  ],
  "naic-chicago": [
    {
      "name": "힐튼 가든 인 시카고 매코믹 플레이스",
      "nameJa": "Hilton Garden Inn Chicago McCormick Place",
      "map": "Hilton Garden Inn Chicago McCormick Place",
      "area": "사우스루프 (123 E Cermak Rd)",
      "near": "McCormick Place와 실내 스카이브리지로 직결, 도보 약 5분",
      "price": "약 220~320 USD(30만~44만원)/박",
      "note": "⭐ 추천 1순위. 대회장과 실내 통로로 연결돼 짐·날씨 걱정 없이 이동. 그린라인 'L'역 2블록, 조식·피트니스."
    },
    {
      "name": "햄프턴 인 시카고 매코믹 플레이스",
      "nameJa": "Hampton Inn Chicago McCormick Place",
      "map": "Hampton Inn Chicago McCormick Place",
      "area": "사우스루프 (123 E Cermak Rd)",
      "near": "McCormick Place 실내 직결, 도보 약 5분",
      "price": "약 180~260 USD(25만~36만원)/박",
      "note": "힐튼 가든 인과 같은 건물. 무료 핫조식·실내 수영장으로 가족 가성비 좋음(자녀 수영장 인기)."
    },
    {
      "name": "스프링힐 스위트 시카고 차이나타운",
      "nameJa": "SpringHill Suites by Marriott Chicago Chinatown",
      "map": "SpringHill Suites by Marriott Chicago Chinatown",
      "area": "차이나타운",
      "near": "McCormick Place 약 1마일·도보 11분/차량 5분",
      "price": "약 170~250 USD(24만~34만원)/박",
      "note": "전 객실 스위트형으로 가족 공간 넉넉. 차이나타운 식당·마트 도보권이라 한식 입맛에도 무난."
    },
    {
      "name": "시카고 사우스루프 호텔",
      "nameJa": "Chicago South Loop Hotel",
      "map": "Chicago South Loop Hotel",
      "area": "사우스루프/브론즈빌 (11 W 26th St)",
      "near": "McCormick Place 약 4블록·차량 3분",
      "price": "약 130~200 USD(18만~28만원)/박",
      "note": "가장 저렴한 대안. 객실당 무료 주차 1대 포함이라 렌터카 이용 시 유리. 전철역 가까움."
    },
    {
      "name": "에어비앤비 (사우스루프·차이나타운)",
      "nameJa": "South Loop / Chinatown Airbnb",
      "map": "South Loop Chicago",
      "area": "사우스루프·차이나타운·브론즈빌",
      "near": "McCormick Place 도보~전철 10분권",
      "price": "위치·인원별 상이",
      "note": "주방·세탁기로 4~5박 장기 체류 시 식비·빨래에 유리하고 공간이 넓어요. 전철역·큰길 인접 숙소를 고르고 후기·환불정책·침대수·에어컨 확인. 한밤 도보 이동은 피하세요."
    }
  ]
}
